Workbook

Sheet Como usar
B2: BRENO BARBIERI · INTELIGÊNCIA COMERCIAL
B3: Calculadora de O.T.E
B4: Fixo, variável e bônus de operação, com os limites que impedem o modelo de virar incentivo ao preenchimento.
B6: O QUE É O.T.E
B7: On-Target Earnings: é a remuneração total esperada quando o profissional atinge exatamente 100% da meta. Corresponde à soma do salário fixo com a remuneração variável prevista para esse nível de desempenho. É a principal referência para definir e comunicar um plano de remuneração variável.
B9: A REGRA DE DESENHO
B10: Usar o CRM corretamente é padrão básico da operação, não feito extraordinário. O bônus de operação existe para acelerar a virada cultural, não para pagar por preenchimento.
B12: OS QUATRO GUARDA-CORPOS
B13: 01 · Teto no bônus de operação | C13: Máximo de 25% do variável. Acima disso, o vendedor passa a otimizar o sistema em vez do resultado, e a empresa paga por comportamento, não por receita. A calculadora avisa quando o limite é ultrapassado.
B14: 02 · Gatilho mínimo de receita | C14: Abaixo de um atingimento mínimo (sugestão: 70%), o bônus de operação não é pago. Sem esse gatilho existe um caminho para ganhar dinheiro sem vender, e o modelo perde legitimidade diante do time que vende.
B15: 03 · Critérios de qualidade, nunca de volume | C15: Os três critérios pré-modelados medem qualidade de pipeline: evidência na passagem de etapa, cumprimento de SLA e acurácia de forecast. Nenhum deles melhora ao se preencher mais campo. Trocar por 'campos preenchidos' ou 'atividades registradas' quebra o modelo.
B16: 04 · Nada é medido no olho | C16: Cada critério precisa sair de um relatório que o vendedor consegue consultar sozinho, a qualquer momento. Critério que só a liderança enxerga vira sensação de arbitrariedade, e destrói a confiança que o bônus deveria construir.
B18: LEGENDA
B19: Azul sobre amarelo | C19: Premissa que você define.
B20: Preto sobre cinza | C20: Calculado. Não edite.
B22: Todos os valores da aba Calculadora são exemplos de partida, não recomendação de remuneração. Calibre com o seu ticket, ciclo de venda e mercado.
B24: Breno Barbieri · Inteligência Comercial · octanesales.com.br

Sheet Calculadora
B2: REMUNERAÇÃO VARIÁVEL
B3: Calculadora de O.T.E
B4: Preencha apenas as células amarelas.
B6: 01 · ESTRUTURA DO PACOTE
B7: O.T.E mensal (100% da meta) | C7: 10000 | E7: O que o vendedor leva no mês em que bate exatamente a meta.
B8: Participação do fixo | C8: 0.5 | E8: Ciclo de venda longo e ticket alto pedem fixo maior; venda transacional suporta variável maior.
B9: Participação do variável | C9: =1-C8 -> 0.5 | E9: Calculado a partir do fixo.
B10: Salário fixo mensal | C10: =C7*C8 -> 5000
B11: Variável no alvo | C11: =C7*C9 -> 5000
B13: 02 · COMPOSIÇÃO DO VARIÁVEL
B14: Parcela ligada a receita | C14: 0.8 | E14: O peso principal. Vendedor é pago por vender.
B15: Parcela ligada a operação (bônus CRM) | C15: =1-C14 -> 0.2 | E15: Teto recomendado: 25%.
B16: Comissão de receita no alvo | C16: =C11*C14 -> 4000
B17: Bônus de operação no alvo | C17: =C11*C15 -> 1000
B18: =IF(C15>0.25,"ALERTA · o bônus de operação está em "&TEXT(C15,"0%")&" do variável, acima do teto de 25%. Nessa faixa o vendedor passa a otimizar o sistema em vez do resultado.",IF(C15=0,"Sem bônus de operação. O modelo é 100% receita: legítimo, mas não acelera adoção.","Dentro do teto recomendado.")) -> Dentro do teto recomendado.
B20: 03 · CRITÉRIOS DE QUALIDADE DO BÔNUS DE OPERAÇÃO
B21: Critério | C21: Peso | D21: Realizado | E21: Como medir
B22: Higiene do gatilho de passagem | C22: 0.4 | D22: 0.85 | E22: % dos avanços de etapa no período com a evidência exigida registrada.
B23: Cumprimento do SLA de primeira resposta | C23: 0.3 | D23: 0.92 | E23: % dos leads atendidos dentro do tempo máximo definido por canal.
B24: Acurácia de forecast | C24: 0.3 | D24: 0.7 | E24: 1 menos o desvio entre o previsto no início do mês e o realizado.
B25: Soma dos pesos | C25: =SUM(C22:C24) -> 1 | D25: =IF(ROUND(C25,4)<>1,"Os pesos precisam somar 100%.","")
B26: Índice de qualidade do período | C26: =IFERROR(SUMPRODUCT(C22:C24,D22:D24)/C25,0) -> 0.826 | E26: Média dos critérios ponderada pelos pesos.
B28: 04 · RESULTADO DO MÊS
B29: Meta de receita do vendedor | C29: 250000
B30: Receita realizada | C30: 212000
B31: Atingimento de receita | C31: =IFERROR(C30/C29,0) -> 0.848
B32: Gatilho mínimo para liberar o bônus de operação | C32: 0.7 | E32: Abaixo deste atingimento, o bônus de operação não é pago. Sem gatilho, existe caminho para ganhar sem vender.
B33: Teto de pagamento da comissão de receita | C33: 1.5 | E33: Limite de aceleração. 1,5x significa que o atingimento é considerado até 150%.
B35: Comissão de receita paga | C35: =C16*MIN(C31,C33) -> 3392
B36: Bônus de operação pago | C36: =IF(C31<C32,0,C17*C26) -> 826 | E36: Zerado enquanto o atingimento de receita estiver abaixo do gatilho.
B37: Fixo | C37: =C10 -> 5000
B38: Remuneração total do mês | C38: =C35+C36+C37 -> 9218
B39: % do O.T.E | C39: =IFERROR(C38/C7,0) -> 0.9218
B40: Custo de venda (remuneração / receita realizada) | C40: =IFERROR(C38/C30,0) -> 0.043481132 | E40: Se este número sobe quando a receita sobe, o plano está mal desenhado.
B42: =IF(ROUND(C8+C9,4)<>1,"ALERTA · fixo e variável precisam somar 100%.",IF(C32=0,"ALERTA · sem gatilho mínimo, o bônus de operação pode ser pago a quem não vendeu.",IF(C31<C32,"O bônus de operação não é pago neste mês: o atingimento de receita ficou abaixo do gatilho.","Plano coerente com os guarda-corpos."))) -> Plano coerente com os guarda-corpos.
B44: Valores de partida são exemplos. Nenhum número aqui é recomendação de remuneração. Calibre com o seu ticket, ciclo e mercado.

Sheet Cenários
B2: SENSIBILIDADE
B3: Quanto o vendedor leva em cada cenário
B4: Remuneração total do mês. Linhas: atingimento de receita. Colunas: índice de qualidade do período.
C5: Qualidade
B6: Atingimento de receita | C6: 0 | D6: 0.6 | E6: 0.85 | F6: 1
B7: 0.5 | C7: =Calculadora!$C$10 + Calculadora!$C$16*MIN($B7,Calculadora!$C$33) + IF($B7<Calculadora!$C$32,0,Calculadora!$C$17*C$6) -> 7000 | D7: =Calculadora!$C$10 + Calculadora!$C$16*MIN($B7,Calculadora!$C$33) + IF($B7<Calculadora!$C$32,0,Calculadora!$C$17*D$6) -> 7000 | E7: =Calculadora!$C$10 + Calculadora!$C$16*MIN($B7,Calculadora!$C$33) + IF($B7<Calculadora!$C$32,0,Calculadora!$C$17*E$6) -> 7000 | F7: =Calculadora!$C$10 + Calculadora!$C$16*MIN($B7,Calculadora!$C$33) + IF($B7<Calculadora!$C$32,0,Calculadora!$C$17*F$6) -> 7000
B8: 0.7 | C8: =Calculadora!$C$10 + Calculadora!$C$16*MIN($B8,Calculadora!$C$33) + IF($B8<Calculadora!$C$32,0,Calculadora!$C$17*C$6) -> 7800 | D8: =Calculadora!$C$10 + Calculadora!$C$16*MIN($B8,Calculadora!$C$33) + IF($B8<Calculadora!$C$32,0,Calculadora!$C$17*D$6) -> 8400 | E8: =Calculadora!$C$10 + Calculadora!$C$16*MIN($B8,Calculadora!$C$33) + IF($B8<Calculadora!$C$32,0,Calculadora!$C$17*E$6) -> 8650 | F8: =Calculadora!$C$10 + Calculadora!$C$16*MIN($B8,Calculadora!$C$33) + IF($B8<Calculadora!$C$32,0,Calculadora!$C$17*F$6) -> 8800
B9: 0.85 | C9: =Calculadora!$C$10 + Calculadora!$C$16*MIN($B9,Calculadora!$C$33) + IF($B9<Calculadora!$C$32,0,Calculadora!$C$17*C$6) -> 8400 | D9: =Calculadora!$C$10 + Calculadora!$C$16*MIN($B9,Calculadora!$C$33) + IF($B9<Calculadora!$C$32,0,Calculadora!$C$17*D$6) -> 9000 | E9: =Calculadora!$C$10 + Calculadora!$C$16*MIN($B9,Calculadora!$C$33) + IF($B9<Calculadora!$C$32,0,Calculadora!$C$17*E$6) -> 9250 | F9: =Calculadora!$C$10 + Calculadora!$C$16*MIN($B9,Calculadora!$C$33) + IF($B9<Calculadora!$C$32,0,Calculadora!$C$17*F$6) -> 9400
B10: 1 | C10: =Calculadora!$C$10 + Calculadora!$C$16*MIN($B10,Calculadora!$C$33) + IF($B10<Calculadora!$C$32,0,Calculadora!$C$17*C$6) -> 9000 | D10: =Calculadora!$C$10 + Calculadora!$C$16*MIN($B10,Calculadora!$C$33) + IF($B10<Calculadora!$C$32,0,Calculadora!$C$17*D$6) -> 9600 | E10: =Calculadora!$C$10 + Calculadora!$C$16*MIN($B10,Calculadora!$C$33) + IF($B10<Calculadora!$C$32,0,Calculadora!$C$17*E$6) -> 9850 | F10: =Calculadora!$C$10 + Calculadora!$C$16*MIN($B10,Calculadora!$C$33) + IF($B10<Calculadora!$C$32,0,Calculadora!$C$17*F$6) -> 10000
B11: 1.2 | C11: =Calculadora!$C$10 + Calculadora!$C$16*MIN($B11,Calculadora!$C$33) + IF($B11<Calculadora!$C$32,0,Calculadora!$C$17*C$6) -> 9800 | D11: =Calculadora!$C$10 + Calculadora!$C$16*MIN($B11,Calculadora!$C$33) + IF($B11<Calculadora!$C$32,0,Calculadora!$C$17*D$6) -> 10400 | E11: =Calculadora!$C$10 + Calculadora!$C$16*MIN($B11,Calculadora!$C$33) + IF($B11<Calculadora!$C$32,0,Calculadora!$C$17*E$6) -> 10650 | F11: =Calculadora!$C$10 + Calculadora!$C$16*MIN($B11,Calculadora!$C$33) + IF($B11<Calculadora!$C$32,0,Calculadora!$C$17*F$6) -> 10800
B12: 1.5 | C12: =Calculadora!$C$10 + Calculadora!$C$16*MIN($B12,Calculadora!$C$33) + IF($B12<Calculadora!$C$32,0,Calculadora!$C$17*C$6) -> 11000 | D12: =Calculadora!$C$10 + Calculadora!$C$16*MIN($B12,Calculadora!$C$33) + IF($B12<Calculadora!$C$32,0,Calculadora!$C$17*D$6) -> 11600 | E12: =Calculadora!$C$10 + Calculadora!$C$16*MIN($B12,Calculadora!$C$33) + IF($B12<Calculadora!$C$32,0,Calculadora!$C$17*E$6) -> 11850 | F12: =Calculadora!$C$10 + Calculadora!$C$16*MIN($B12,Calculadora!$C$33) + IF($B12<Calculadora!$C$32,0,Calculadora!$C$17*F$6) -> 12000
B14: Leia a coluna de qualidade 0%: é o que o vendedor leva se vender e ignorar o processo. A distância entre essa coluna e a de 100% é o tamanho real do incentivo que você está oferecendo. Se for pequena demais, ninguém muda comportamento; se for grande demais, o time otimiza o sistema em vez da venda.
B16: Breno Barbieri · Inteligência Comercial · octanesales.com.br
