Workbook

Sheet Como usar
B2: BRENO BARBIERI · INTELIGÊNCIA COMERCIAL
B3: Daily comercial
B4: Quinze minutos, quatro perguntas, o sistema aberto na tela.
B6: A REGRA DE OURO
B7: Quer falar de venda? Abre o sistema. Se não está registrado, não pode virar base de decisão.
B9: AS QUATRO PERGUNTAS
B10: 01 O que avançou de oportunidade ontem? | C10: Confere movimento real, não esforço. Avanço sem critério de passagem é card empurrado. A coluna 'De qual etapa veio' existe para isso ficar visível.
B11: 02 Qual oportunidade mais próxima do fechamento vamos tracionar hoje? | C11: Foco. A daily não revisa o pipeline inteiro: escolhe onde a energia do dia vai. Toda oportunidade tracionada sai da reunião com próximo passo e data.
B12: 03 Onde a minha entrada hoje pode acelerar algum fechamento? | C12: O líder se oferece antes de ser pedido. Registrar isso torna visível se a liderança está destravando negócio ou apenas cobrando número.
B13: 04 Tem alguma oportunidade agarrada? Por quê? | C13: A pergunta mais valiosa da reunião. O motivo do travamento é categorizado de propósito: em quatro semanas, a coluna vira um diagnóstico de onde o seu funil vaza.
B15: COMO RODAR
B16: Quem conduz | C16: O líder comercial. Em pé, câmera aberta, sistema compartilhado na tela.
B17: Duração | C17: 15 minutos. Passou disso, virou reunião de pipeline, que é outro rito, semanal.
B18: Quantas oportunidades | C18: De três a seis por vendedor. A daily prioriza; não faz a varredura completa do funil.
B19: O que não entra | C19: Oportunidade que não está no sistema. Registrar na hora vale mais que discutir de memória.
B20: Preenchimento | C20: Uma linha por oportunidade discutida, por dia. Preencha durante a reunião, não depois.
B22: LEGENDA DE PREENCHIMENTO
B23: Célula amarela | C23: Você preenche.
B24: Célula branca | C24: Você preenche (texto livre).
B25: Célula cinza | C25: Calculada. Não edite.
B27: A aba Painel lê a aba Daily automaticamente. Rode quatro semanas antes de tirar conclusão: um motivo de travamento concentrado acima de 30% deixa de ser caso isolado e passa a ser gargalo de processo.
B29: Breno Barbieri · Inteligência Comercial · octanesales.com.br

Sheet Daily
A1: DAILY COMERCIAL
A2: Uma linha por oportunidade discutida, por dia.
A3: Quer falar de venda? Abre o sistema. Se não está registrado, não pode virar base de decisão.
A5: Data | B5: Vendedor | C5: Oportunidade / cliente | D5: Valor (R$) | E5: Etapa atual | F5: P1 · Avançou desde ontem? | G5: P1 · Veio de qual etapa | H5: P2 · Traciona hoje? | I5: P2 · Próximo passo definido | J5: P2 · Data do passo | K5: P3 · Precisa do líder? | L5: P3 · Qual entrada do líder | M5: P4 · Está agarrada? | N5: P4 · Motivo do travamento | O5: Dias na etapa | P5: Alerta
A6: =TODAY() -> 46231 | B6: Ana Prado | C6: Metalúrgica Vertex · 40 licenças | D6: 48000 | E6: Proposta | F6: Sim | G6: Diagnóstico/Reunião | H6: Sim | I6: Call com o diretor financeiro para revisar condição de pagamento | J6: =TODAY()+1 -> 46232 | K6: Sim | L6: Entrar na call como especialista para sustentar o valor | M6: Não | O6: 6 | P6: =IF(C6="","",IF(AND(M6="Sim",N6=""),"Agarrada sem motivo declarado",IF(AND(H6="Sim",I6=""),"Traciona hoje sem próximo passo",IF(AND(O6<>"",O6>=14),"Parada há 14 dias ou mais",IF(AND(M6="Sim",O6<>"",O6>=7),"Agarrada há 7 dias, escalar",IF(AND(I6<>"",J6=""),"Próximo passo sem data",""))))))
P7: =IF(C7="","",IF(AND(M7="Sim",N7=""),"Agarrada sem motivo declarado",IF(AND(H7="Sim",I7=""),"Traciona hoje sem próximo passo",IF(AND(O7<>"",O7>=14),"Parada há 14 dias ou mais",IF(AND(M7="Sim",O7<>"",O7>=7),"Agarrada há 7 dias, escalar",IF(AND(I7<>"",J7=""),"Próximo passo sem data",""))))))
P8: =IF(C8="","",IF(AND(M8="Sim",N8=""),"Agarrada sem motivo declarado",IF(AND(H8="Sim",I8=""),"Traciona hoje sem próximo passo",IF(AND(O8<>"",O8>=14),"Parada há 14 dias ou mais",IF(AND(M8="Sim",O8<>"",O8>=7),"Agarrada há 7 dias, escalar",IF(AND(I8<>"",J8=""),"Próximo passo sem data",""))))))
P9: =IF(C9="","",IF(AND(M9="Sim",N9=""),"Agarrada sem motivo declarado",IF(AND(H9="Sim",I9=""),"Traciona hoje sem próximo passo",IF(AND(O9<>"",O9>=14),"Parada há 14 dias ou mais",IF(AND(M9="Sim",O9<>"",O9>=7),"Agarrada há 7 dias, escalar",IF(AND(I9<>"",J9=""),"Próximo passo sem data",""))))))
P10: =IF(C10="","",IF(AND(M10="Sim",N10=""),"Agarrada sem motivo declarado",IF(AND(H10="Sim",I10=""),"Traciona hoje sem próximo passo",IF(AND(O10<>"",O10>=14),"Parada há 14 dias ou mais",IF(AND(M10="Sim",O10<>"",O10>=7),"Agarrada há 7 dias, escalar",IF(AND(I10<>"",J10=""),"Próximo passo sem data",""))))))
P11: =IF(C11="","",IF(AND(M11="Sim",N11=""),"Agarrada sem motivo declarado",IF(AND(H11="Sim",I11=""),"Traciona hoje sem próximo passo",IF(AND(O11<>"",O11>=14),"Parada há 14 dias ou mais",IF(AND(M11="Sim",O11<>"",O11>=7),"Agarrada há 7 dias, escalar",IF(AND(I11<>"",J11=""),"Próximo passo sem data",""))))))
P12: =IF(C12="","",IF(AND(M12="Sim",N12=""),"Agarrada sem motivo declarado",IF(AND(H12="Sim",I12=""),"Traciona hoje sem próximo passo",IF(AND(O12<>"",O12>=14),"Parada há 14 dias ou mais",IF(AND(M12="Sim",O12<>"",O12>=7),"Agarrada há 7 dias, escalar",IF(AND(I12<>"",J12=""),"Próximo passo sem data",""))))))
P13: =IF(C13="","",IF(AND(M13="Sim",N13=""),"Agarrada sem motivo declarado",IF(AND(H13="Sim",I13=""),"Traciona hoje sem próximo passo",IF(AND(O13<>"",O13>=14),"Parada há 14 dias ou mais",IF(AND(M13="Sim",O13<>"",O13>=7),"Agarrada há 7 dias, escalar",IF(AND(I13<>"",J13=""),"Próximo passo sem data",""))))))
P14: =IF(C14="","",IF(AND(M14="Sim",N14=""),"Agarrada sem motivo declarado",IF(AND(H14="Sim",I14=""),"Traciona hoje sem próximo passo",IF(AND(O14<>"",O14>=14),"Parada há 14 dias ou mais",IF(AND(M14="Sim",O14<>"",O14>=7),"Agarrada há 7 dias, escalar",IF(AND(I14<>"",J14=""),"Próximo passo sem data",""))))))
P15: =IF(C15="","",IF(AND(M15="Sim",N15=""),"Agarrada sem motivo declarado",IF(AND(H15="Sim",I15=""),"Traciona hoje sem próximo passo",IF(AND(O15<>"",O15>=14),"Parada há 14 dias ou mais",IF(AND(M15="Sim",O15<>"",O15>=7),"Agarrada há 7 dias, escalar",IF(AND(I15<>"",J15=""),"Próximo passo sem data",""))))))
P16: =IF(C16="","",IF(AND(M16="Sim",N16=""),"Agarrada sem motivo declarado",IF(AND(H16="Sim",I16=""),"Traciona hoje sem próximo passo",IF(AND(O16<>"",O16>=14),"Parada há 14 dias ou mais",IF(AND(M16="Sim",O16<>"",O16>=7),"Agarrada há 7 dias, escalar",IF(AND(I16<>"",J16=""),"Próximo passo sem data",""))))))
P17: =IF(C17="","",IF(AND(M17="Sim",N17=""),"Agarrada sem motivo declarado",IF(AND(H17="Sim",I17=""),"Traciona hoje sem próximo passo",IF(AND(O17<>"",O17>=14),"Parada há 14 dias ou mais",IF(AND(M17="Sim",O17<>"",O17>=7),"Agarrada há 7 dias, escalar",IF(AND(I17<>"",J17=""),"Próximo passo sem data",""))))))
P18: =IF(C18="","",IF(AND(M18="Sim",N18=""),"Agarrada sem motivo declarado",IF(AND(H18="Sim",I18=""),"Traciona hoje sem próximo passo",IF(AND(O18<>"",O18>=14),"Parada há 14 dias ou mais",IF(AND(M18="Sim",O18<>"",O18>=7),"Agarrada há 7 dias, escalar",IF(AND(I18<>"",J18=""),"Próximo passo sem data",""))))))
... P505: =IF(C505="","",IF(AND(M505="Sim",N505=""),"Agarrada sem motivo declarado",IF(AND(H505="Sim",I505=""),"Traciona hoje sem próximo passo",IF(AND(O505<>"",O505>=14),"Parada há 14 dias ou mais",IF(AND(M505="Sim",O505<>"",O505>=7),"Agarrada há 7 dias, escalar",IF(AND(I505<>"",J505=""),"Próximo passo sem data",""))))))
A507: Linha 6 é um exemplo de preenchimento. Apague antes de usar. Fórmulas da coluna Alerta já estão prontas até a linha 505.

Sheet Painel
B2: LEITURA DA OPERAÇÃO
B3: O que a sua daily está dizendo
B4: Calculado sobre tudo o que já foi registrado na aba Daily.
B6: VOLUME
B7: Oportunidades registradas na daily | C7: =COUNTA(Daily!$C$6:$C$505) -> 1
B8: Valor total em discussão | C8: =SUMIFS(Daily!$D$6:$D$505,Daily!$C$6:$C$505,"<>") -> 48000
B9: Oportunidades agarradas | C9: =COUNTIF(Daily!$M$6:$M$505,"Sim") -> 0
B10: % agarradas | C10: =IFERROR(COUNTIF(Daily!$M$6:$M$505,"Sim")/COUNTA(Daily!$C$6:$C$505),0) -> 0
B11: Valor travado em oportunidades agarradas | C11: =SUMIFS(Daily!$D$6:$D$505,Daily!$M$6:$M$505,"Sim") -> 0
B12: Tempo médio parado nas agarradas (dias) | C12: =IFERROR(AVERAGEIF(Daily!$M$6:$M$505,"Sim",Daily!$O$6:$O$505),0) -> 0
B13: % das tracionadas com próximo passo definido | C13: =IFERROR(COUNTIFS(Daily!$H$6:$H$505,"Sim",Daily!$I$6:$I$505,"<>")/COUNTIF(Daily!$H$6:$H$505,"Sim"),0) -> 1
B15: ONDE O FUNIL TRAVA
B16: Motivo declarado | C16: Casos | D16: Valor travado | E16: Leitura · se este motivo concentrar, o gargalo é este
B17: Sem acesso a quem decide | C17: =COUNTIF(Daily!$N$6:$N$505,B17) -> 0 | D17: =SUMIFS(Daily!$D$6:$D$505,Daily!$N$6:$N$505,B17) -> 0 | E17: Qualificação: o funil avança sem o decisor mapeado. Gatilho de passagem fraco na entrada.
B18: Dor não validada na qualificação | C18: =COUNTIF(Daily!$N$6:$N$505,B18) -> 0 | D18: =SUMIFS(Daily!$D$6:$D$505,Daily!$N$6:$N$505,B18) -> 0 | E18: Qualificação: proposta enviada antes da dor estar validada. Etapa queimada.
B19: Preço acima do orçamento do cliente | C19: =COUNTIF(Daily!$N$6:$N$505,B19) -> 0 | D19: =SUMIFS(Daily!$D$6:$D$505,Daily!$N$6:$N$505,B19) -> 0 | E19: ICP ou proposta de valor: você está atraindo quem não tem orçamento, ou não sustenta o preço.
B20: Concorrente na disputa | C20: =COUNTIF(Daily!$N$6:$N$505,B20) -> 0 | D20: =SUMIFS(Daily!$D$6:$D$505,Daily!$N$6:$N$505,B20) -> 0 | E20: Diferenciação: o valor não está claro o bastante para o cliente escolher sem comparar preço.
B21: Timing do cliente (adiado) | C21: =COUNTIF(Daily!$N$6:$N$505,B21) -> 0 | D21: =SUMIFS(Daily!$D$6:$D$505,Daily!$N$6:$N$505,B21) -> 0 | E21: Timing é o motivo mais confortável de declarar. Concentração alta aqui costuma esconder falta de urgência construída na conversa.
B22: Falta follow-up nosso | C22: =COUNTIF(Daily!$N$6:$N$505,B22) -> 0 | D22: =SUMIFS(Daily!$D$6:$D$505,Daily!$N$6:$N$505,B22) -> 0 | E22: Processo: o problema é seu, não do cliente. Cadência e SLA resolvem. É o mais barato de corrigir.
B23: Aguardando entrega de algo nosso | C23: =COUNTIF(Daily!$N$6:$N$505,B23) -> 0 | D23: =SUMIFS(Daily!$D$6:$D$505,Daily!$N$6:$N$505,B23) -> 0 | E23: Operação interna: a venda depende de uma entrega que você não controla. Vira problema de capacidade, não de vendas.
B24: Não sabemos, falta registro | C24: =COUNTIF(Daily!$N$6:$N$505,B24) -> 0 | D24: =SUMIFS(Daily!$D$6:$D$505,Daily!$N$6:$N$505,B24) -> 0 | E24: Registro: o time não sabe por que o negócio parou. Sem isso, nenhuma leitura acima é confiável.
B25: Total declarado | C25: =SUM(C17:C24) -> 0 | D25: =SUM(D17:D24) -> 0
B27: CONCENTRAÇÃO PRINCIPAL
B28: =IF(SUM(C17:C24)=0,"Sem dados suficientes. Registre pelo menos duas semanas de daily.",INDEX(B17:B24,MATCH(MAX(C17:C24),C17:C24,0))) -> Sem dados suficientes. Registre pelo menos duas semanas de daily.
B29: =IF(SUM(C17:C24)=0,"","Representa "&TEXT(MAX(C17:C24)/SUM(C17:C24),"0%")&" dos travamentos declarados. Acima de 30% em quatro semanas, isto deixa de ser caso isolado e passa a ser gargalo de processo.")
B31: Este painel classifica onde a operação trava. Ele não mede quanto isso custa. Para isso é preciso reconstruir o funil com conversão por etapa, ciclo de venda e unit economics.
B33: Breno Barbieri · Inteligência Comercial · octanesales.com.br

Sheet Listas
A1: Motivos de travamento | C1: Etapas do funil (edite conforme o seu funil) | E1: Sim/Não
A2: Sem acesso a quem decide | C2: Primeiro contato | E2: Sim
A3: Dor não validada na qualificação | C3: Qualificação | E3: Não
A4: Preço acima do orçamento do cliente | C4: Diagnóstico/Reunião
A5: Concorrente na disputa | C5: Proposta
A6: Timing do cliente (adiado) | C6: Negociação
A7: Falta follow-up nosso | C7: Fechamento
A8: Aguardando entrega de algo nosso
A9: Não sabemos, falta registro
